backtester/Backtester.py
backtester/__init__.py
backtester/config.py
backtester/data_utils.py
backtester/indicators.py
backtester/symbols.py
backtester/trade_analysis.py
backtester/trade_execution.py
united_backtester_japy_v1-0.23.dist-info/licenses/LICENSE
united_backtester_japy_v1-0.23.dist-info/METADATA
united_backtester_japy_v1-0.23.dist-info/WHEEL
united_backtester_japy_v1-0.23.dist-info/top_level.txt
united_backtester_japy_v1-0.23.dist-info/RECORD
