Metadata-Version: 2.4
Name: united_backtester_japy_v1
Version: 0.23
Requires-Python: >=3.7
License-File: LICENSE
Requires-Dist: pandas
Requires-Dist: numpy
Requires-Dist: matplotlib
Requires-Dist: requests
Requires-Dist: python-binance
Requires-Dist: openpyxl
Requires-Dist: pandas-ta-openbb
Requires-Dist: pytz
Requires-Dist: tqdm
Requires-Dist: xlsxwriter
Dynamic: description
Dynamic: description-content-type
Dynamic: license-file
Dynamic: requires-dist
Dynamic: requires-python
